panda3d_sqs/__init__.py
panda3d_sqs/listener.py
panda3d_sqs-1.0.0.dist-info/LICENSE
panda3d_sqs-1.0.0.dist-info/METADATA
panda3d_sqs-1.0.0.dist-info/WHEEL
panda3d_sqs-1.0.0.dist-info/top_level.txt
panda3d_sqs-1.0.0.dist-info/RECORD
